Metadata-Version: 2.4
Name: rffickle
Version: 0.2.2
Summary: Roboflow fork of fickle - load pickled data as safely as possible
Home-page: https://github.com/roboflow/fickle
Author: Eduard Christian Dumitrescu, Roboflow Inc.
Author-email: help@roboflow.com
License: MIT
Classifier: Programming Language :: Python :: 3
Classifier: License :: OSI Approved :: MIT License
Classifier: Operating System :: OS Independent
Requires-Dist: attrs
Dynamic: author
Dynamic: author-email
Dynamic: classifier
Dynamic: description
Dynamic: description-content-type
Dynamic: home-page
Dynamic: license
Dynamic: requires-dist
Dynamic: summary
